cathodic_collect-0.1.6.dist-info/METADATA
cathodic_collect-0.1.6.dist-info/WHEEL
cathodic_collect-0.1.6.dist-info/entry_points.txt
cathodic_collect/__init__.py
cathodic_collect/collect.py
cathodic_collect/const.py
cathodic_collect/drop.py
cathodic_collect/fileutils.py
cathodic_collect/fn.py
cathodic_collect/forms.py
cathodic_collect/gen.py
cathodic_collect/myreader.py
cathodic_collect/reader/__init__.py
cathodic_collect/reader/device.py
cathodic_collect/reader/dfreader.py
cathodic_collect/reader/distance.py
cathodic_collect/reader/file_reader.py
cathodic_collect/reader/graph.py
cathodic_collect/reader/resis.py
cathodic_collect/reader/stage.py
cathodic_collect/s.py
cathodic_collect/shortcut/__init__.py
cathodic_collect/shortcut/device.py
cathodic_collect/shortcut/graph.py
cathodic_collect/tools.py
cathodic_collect/utils.py
cathodic_collect/writer.py
cathodic_collect-0.1.6.dist-info/RECORD
