Metadata-Version: 2.1
Name: cathodic-collect
Version: 0.1.6
Summary: Default template for PDM package
Author-Email: svtter <svtter@qq.com>
License: MIT
Requires-Python: ==3.11.*
Requires-Dist: cathodic-report>=0.1.6
Requires-Dist: pandas>=2.2.3
Requires-Dist: pyyaml>=6.0.2
